flask_manifest.py
Flask_Manifest-0.2.0.dist-info/DESCRIPTION.rst
Flask_Manifest-0.2.0.dist-info/METADATA
Flask_Manifest-0.2.0.dist-info/metadata.json
Flask_Manifest-0.2.0.dist-info/RECORD
Flask_Manifest-0.2.0.dist-info/top_level.txt
Flask_Manifest-0.2.0.dist-info/WHEEL
