Metadata-Version: 2.0
Name: Flask-Manifest
Version: 0.2.0
Summary: Asset manifest integration with Flask.
Home-page: https://github.com/ryankask/flask-manifest
Author: Ryan Kaskel
Author-email: dev@ryankaskel.com
License: BSD
Platform: any
Classifier: Development Status :: 1 - Planning
Classifier: Environment :: Web Environment
Classifier: Intended Audience :: Developers
Classifier: License :: OSI Approved :: BSD License
Classifier: Operating System :: OS Independent
Classifier: Programming Language :: Python
Classifier: Topic :: Internet :: WWW/HTTP :: Dynamic Content
Classifier: Topic :: Software Development :: Libraries :: Python Modules
Requires-Dist: Flask
